logfile_parser/__init__.py
logfile_parser/grammars/cExperiment_log_format.json
logfile_parser/grammars/multiDGUI_acq_format.json
logfile_parser/grammars/multiDGUI_log_format.json
logfile_parser/logfile_parser.py
aliby_parser-0.1.9.dist-info/LICENSE
aliby_parser-0.1.9.dist-info/WHEEL
aliby_parser-0.1.9.dist-info/METADATA
aliby_parser-0.1.9.dist-info/RECORD
